clad_sdk/__init__.py
clad_sdk/client.py
clad_ai_python-0.1.5.dist-info/METADATA
clad_ai_python-0.1.5.dist-info/WHEEL
clad_ai_python-0.1.5.dist-info/top_level.txt
clad_ai_python-0.1.5.dist-info/RECORD
