Metadata-Version: 2.4
Name: clad-ai-python
Version: 0.1.5
Summary: Internal Python SDK for injecting AI-native ads
Author: Clad Labs
Requires-Python: >=3.8
Requires-Dist: httpx>=0.24.0
Requires-Dist: cachetools>=5.0.0
Provides-Extra: redis
Requires-Dist: redis>=5.0.0; extra == "redis"
